{
  "attributes": {
  },
  "suggestions": {
  },
  "recipes": {
    "man": "Installs man package"
  },
  "license": "Apache 2.0",
  "conflicting": {
  },
  "dependencies": {
  },
  "providing": {
  },
  "long_description": "",
  "name": "man",
  "platforms": {
    "ubuntu": [

    ],
    "fedora": [

    ],
    "centos": [

    ],
    "redhat": [

    ],
    "debian": [

    ]
  },
  "maintainer": "Opscode, Inc.",
  "description": "Installs man-db",
  "version": "0.7.1",
  "replacing": {
  },
  "maintainer_email": "cookbooks@opscode.com",
  "groupings": {
  },
  "recommendations": {
  }
}