{
  "attributes": {
  },
  "suggestions": {
    "drbd": [

    ]
  },
  "recipes": {
    "heartbeat": "Installs, but does not configure, heartbeat"
  },
  "license": "Apache 2.0",
  "conflicting": {
  },
  "dependencies": {
  },
  "providing": {
  },
  "long_description": "",
  "name": "heartbeat",
  "platforms": {
    "ubuntu": [

    ],
    "debian": [

    ]
  },
  "maintainer": "Opscode, Inc.",
  "description": "Installs but does not configure heartbeat",
  "version": "0.7.0",
  "replacing": {
  },
  "maintainer_email": "cookbooks@opscode.com",
  "groupings": {
  },
  "recommendations": {
  }
}